Workbook

Sheet Registro
A1: REGISTRO DE GASTOS — GIMNASIO
A2: Controla cada gasto con categoría, proveedor y crédito fiscal
A4: Fecha | B4: Categoría | C4: Descripción | D4: Comprobante | E4: RUC Proveedor | F4: Subtotal | G4: IGV 18% | H4: Total | I4: Mes | J4: Detalle
A5: 46157 | B5: Insumos | C5: Compra de mercadería | D5: Factura | F5: 627.06 | G5: =ROUND(F5*0.18,2) | H5: =F5+G5 | I5: May
A6: 46185 | B6: Marketing | C6: Imprevisto | D6: Factura | E6: 20875666129 | F6: 33.69 | G6: =ROUND(F6*0.18,2) | H6: =F6+G6 | I6: Jun
A7: 46176 | B7: Marketing | C7: Sueldo personal | D7: Factura | E7: 20972148163 | F7: 857.39 | G7: =ROUND(F7*0.18,2) | H7: =F7+G7 | I7: Jun
A8: 46150 | B8: Personal | C8: Imprevisto | D8: Factura | E8: 20298623912 | F8: 612.17 | G8: =ROUND(F8*0.18,2) | H8: =F8+G8 | I8: May
A9: 46156 | B9: Personal | C9: Sueldo personal | D9: Factura | F9: 413.07 | G9: =ROUND(F9*0.18,2) | H9: =F9+G9 | I9: May
A10: 46085 | B10: Alquiler | C10: Compra de mercadería | D10: Factura | F10: 226.99 | G10: =ROUND(F10*0.18,2) | H10: =F10+G10 | I10: Mar
A11: 46023 | B11: Transporte | C11: Alquiler mensual | D11: Factura | E11: 20361806235 | F11: 260.22 | G11: =ROUND(F11*0.18,2) | H11: =F11+G11 | I11: Ene
A12: 46151 | B12: Transporte | C12: Recibo de luz ENEL | D12: Factura | F12: 114.46 | G12: =ROUND(F12*0.18,2) | H12: =F12+G12 | I12: May
A13: 46040 | B13: Servicios | C13: Compra de mercadería | D13: Factura | E13: 20621574297 | F13: 73.67 | G13: =ROUND(F13*0.18,2) | H13: =F13+G13 | I13: Ene
A14: 46123 | B14: Insumos | C14: Combustible | D14: Factura | E14: 20125890439 | F14: 138.76 | G14: =ROUND(F14*0.18,2) | H14: =F14+G14 | I14: Abr
A15: 46154 | B15: Personal | C15: Combustible | D15: Factura | F15: 163.43 | G15: =ROUND(F15*0.18,2) | H15: =F15+G15 | I15: May
A16: 46218 | B16: Insumos | C16: Flete de carga | D16: Factura | E16: 20762319550 | F16: 667.95 | G16: =ROUND(F16*0.18,2) | H16: =F16+G16 | I16: Jul
A17: 46090 | B17: Personal | C17: Agua SEDAPAL | D17: Factura | E17: 20707157578 | F17: 307.69 | G17: =ROUND(F17*0.18,2) | H17: =F17+G17 | I17: Mar
A18: 46130 | B18: Transporte | C18: Combustible | D18: Factura | E18: 20311271710 | F18: 892.21 | G18: =ROUND(F18*0.18,2) | H18: =F18+G18 | I18: Abr
A19: 46127 | B19: Alquiler | C19: Combustible | D19: Boleta | E19: 20445769695 | F19: 811.46 | G19: =ROUND(F19*0.18,2) | H19: =F19+G19 | I19: Abr
A20: 46128 | B20: Marketing | C20: Combustible | D20: Boleta | E20: 20113202257 | F20: 815.28 | G20: =ROUND(F20*0.18,2) | H20: =F20+G20 | I20: Abr
A21: 46107 | B21: Insumos | C21: Combustible | D21: Boleta | E21: 20628106997 | F21: 99.98 | G21: =ROUND(F21*0.18,2) | H21: =F21+G21 | I21: Mar
A22: 46213 | B22: Personal | C22: Recibo de luz ENEL | D22: Factura | E22: 20326265566 | F22: 91.67 | G22: =ROUND(F22*0.18,2) | H22: =F22+G22 | I22: Jul
A23: 46040 | B23: Alquiler | C23: Internet Claro | D23: Factura | E23: 20553116885 | F23: 209.16 | G23: =ROUND(F23*0.18,2) | H23: =F23+G23 | I23: Ene
A24: 46055 | B24: Transporte | C24: Recibo de luz ENEL | D24: Factura | F24: 650.83 | G24: =ROUND(F24*0.18,2) | H24: =F24+G24 | I24: Feb
A25: 46060 | B25: Alquiler | C25: Recibo de luz ENEL | D25: Factura | E25: 20984023867 | F25: 877.78 | G25: =ROUND(F25*0.18,2) | H25: =F25+G25 | I25: Feb
A26: 46158 | B26: Alquiler | C26: Alquiler mensual | D26: Factura | F26: 481.81 | G26: =ROUND(F26*0.18,2) | H26: =F26+G26 | I26: May
F27: =SUM(F5:F26) | G27: =SUM(G5:G26) | H27: =SUM(H5:H26)

Sheet Resumen
A1: RESUMEN DE GASTOS — GIMNASIO
A2: Distribución por categoría y crédito fiscal IGV
A4: TOTAL GASTOS | D4: IGV CRÉDITO FISCAL
A5: =SUM(Registro!H5:H26) | D5: =SUM(Registro!G5:G26)
A8: GASTOS POR CATEGORÍA
A9: Categoría | B9: Monto | C9: % del total | D9: Registros
A10: Insumos | B10: =SUMIF(Registro!$B:$B,A10,Registro!$H:$H) | C10: =IF(SUM(Registro!$H$5:$H$26)=0,0,B10/SUM(Registro!$H$5:$H$26)) | D10: =COUNTIF(Registro!$B:$B,A10)
A11: Alquiler | B11: =SUMIF(Registro!$B:$B,A11,Registro!$H:$H) | C11: =IF(SUM(Registro!$H$5:$H$26)=0,0,B11/SUM(Registro!$H$5:$H$26)) | D11: =COUNTIF(Registro!$B:$B,A11)
A12: Servicios | B12: =SUMIF(Registro!$B:$B,A12,Registro!$H:$H) | C12: =IF(SUM(Registro!$H$5:$H$26)=0,0,B12/SUM(Registro!$H$5:$H$26)) | D12: =COUNTIF(Registro!$B:$B,A12)
A13: Personal | B13: =SUMIF(Registro!$B:$B,A13,Registro!$H:$H) | C13: =IF(SUM(Registro!$H$5:$H$26)=0,0,B13/SUM(Registro!$H$5:$H$26)) | D13: =COUNTIF(Registro!$B:$B,A13)
A14: Marketing | B14: =SUMIF(Registro!$B:$B,A14,Registro!$H:$H) | C14: =IF(SUM(Registro!$H$5:$H$26)=0,0,B14/SUM(Registro!$H$5:$H$26)) | D14: =COUNTIF(Registro!$B:$B,A14)
A15: Transporte | B15: =SUMIF(Registro!$B:$B,A15,Registro!$H:$H) | C15: =IF(SUM(Registro!$H$5:$H$26)=0,0,B15/SUM(Registro!$H$5:$H$26)) | D15: =COUNTIF(Registro!$B:$B,A15)
A18: RESUMEN IGV
A19: Concepto | B19: Monto
A20: IGV pagado (crédito fiscal) | B20: =SUM(Registro!G5:G26)
A21: Total gastos con IGV | B21: =SUM(Registro!H5:H26)
A22: Promedio mensual | B22: =SUM(Registro!H5:H26)/7
A24: 💡 El IGV del 18% se calcula automáticamente. Útil para la declaración mensual.
A26: Gimnasio · Plantilla profesional Pack Perú
