Workbook

Sheet Panel
A1: DASHBOARD FINANCIERO — MERCADO DE ABASTOS
A2: Organiza, analiza y toma mejores decisiones · Todo se calcula automáticamente
A4: INGRESOS TOTALES | D4: GASTOS TOTALES | G4: UTILIDAD
A5: =SUM(Ingresos!G5:G28) | D5: =SUM(Gastos!G5:G28) | G5: =SUM(Ingresos!G5:G28)-SUM(Gastos!G5:G28)
A8: EVOLUCIÓN MENSUAL | F8: DISTRIBUCIÓN DE GASTOS
A9: Mes | B9: Ingresos | C9: Gastos | D9: Utilidad | E9: Margen | F9: Categoría | G9: Monto | H9: %
A10: Ene | B10: =SUMIF(Ingresos!$H:$H,A10,Ingresos!$G:$G) | C10: =SUMIF(Gastos!$H:$H,A10,Gastos!$G:$G) | D10: =B10-C10 | E10: =IF(B10=0,0,D10/B10) | F10: Insumos | G10: =SUMIF(Gastos!$C:$C,F10,Gastos!$G:$G) | H10: =IF(SUM(Gastos!$G$5:$G$28)=0,0,G10/SUM(Gastos!$G$5:$G$28))
A11: Feb | B11: =SUMIF(Ingresos!$H:$H,A11,Ingresos!$G:$G) | C11: =SUMIF(Gastos!$H:$H,A11,Gastos!$G:$G) | D11: =B11-C11 | E11: =IF(B11=0,0,D11/B11) | F11: Alquiler | G11: =SUMIF(Gastos!$C:$C,F11,Gastos!$G:$G) | H11: =IF(SUM(Gastos!$G$5:$G$28)=0,0,G11/SUM(Gastos!$G$5:$G$28))
A12: Mar | B12: =SUMIF(Ingresos!$H:$H,A12,Ingresos!$G:$G) | C12: =SUMIF(Gastos!$H:$H,A12,Gastos!$G:$G) | D12: =B12-C12 | E12: =IF(B12=0,0,D12/B12) | F12: Servicios | G12: =SUMIF(Gastos!$C:$C,F12,Gastos!$G:$G) | H12: =IF(SUM(Gastos!$G$5:$G$28)=0,0,G12/SUM(Gastos!$G$5:$G$28))
A13: Abr | B13: =SUMIF(Ingresos!$H:$H,A13,Ingresos!$G:$G) | C13: =SUMIF(Gastos!$H:$H,A13,Gastos!$G:$G) | D13: =B13-C13 | E13: =IF(B13=0,0,D13/B13) | F13: Personal | G13: =SUMIF(Gastos!$C:$C,F13,Gastos!$G:$G) | H13: =IF(SUM(Gastos!$G$5:$G$28)=0,0,G13/SUM(Gastos!$G$5:$G$28))
A14: May | B14: =SUMIF(Ingresos!$H:$H,A14,Ingresos!$G:$G) | C14: =SUMIF(Gastos!$H:$H,A14,Gastos!$G:$G) | D14: =B14-C14 | E14: =IF(B14=0,0,D14/B14) | F14: Marketing | G14: =SUMIF(Gastos!$C:$C,F14,Gastos!$G:$G) | H14: =IF(SUM(Gastos!$G$5:$G$28)=0,0,G14/SUM(Gastos!$G$5:$G$28))
A15: Jun | B15: =SUMIF(Ingresos!$H:$H,A15,Ingresos!$G:$G) | C15: =SUMIF(Gastos!$H:$H,A15,Gastos!$G:$G) | D15: =B15-C15 | E15: =IF(B15=0,0,D15/B15) | F15: Transporte | G15: =SUMIF(Gastos!$C:$C,F15,Gastos!$G:$G) | H15: =IF(SUM(Gastos!$G$5:$G$28)=0,0,G15/SUM(Gastos!$G$5:$G$28))
A16: Jul | B16: =SUMIF(Ingresos!$H:$H,A16,Ingresos!$G:$G) | C16: =SUMIF(Gastos!$H:$H,A16,Gastos!$G:$G) | D16: =B16-C16 | E16: =IF(B16=0,0,D16/B16)
A17: Ago | B17: =SUMIF(Ingresos!$H:$H,A17,Ingresos!$G:$G) | C17: =SUMIF(Gastos!$H:$H,A17,Gastos!$G:$G) | D17: =B17-C17 | E17: =IF(B17=0,0,D17/B17)
A18: Sep | B18: =SUMIF(Ingresos!$H:$H,A18,Ingresos!$G:$G) | C18: =SUMIF(Gastos!$H:$H,A18,Gastos!$G:$G) | D18: =B18-C18 | E18: =IF(B18=0,0,D18/B18)
A19: Oct | B19: =SUMIF(Ingresos!$H:$H,A19,Ingresos!$G:$G) | C19: =SUMIF(Gastos!$H:$H,A19,Gastos!$G:$G) | D19: =B19-C19 | E19: =IF(B19=0,0,D19/B19)
A20: Nov | B20: =SUMIF(Ingresos!$H:$H,A20,Ingresos!$G:$G) | C20: =SUMIF(Gastos!$H:$H,A20,Gastos!$G:$G) | D20: =B20-C20 | E20: =IF(B20=0,0,D20/B20)
A21: Dic | B21: =SUMIF(Ingresos!$H:$H,A21,Ingresos!$G:$G) | C21: =SUMIF(Gastos!$H:$H,A21,Gastos!$G:$G) | D21: =B21-C21 | E21: =IF(B21=0,0,D21/B21)
A22: TOTAL | B22: =SUM(B10:B21) | C22: =SUM(C10:C21) | D22: =SUM(D10:D21)
A24: 💡 Los datos son de ejemplo: reemplázalos con los tuyos en las hojas Ingresos y Gastos.
A34: Más plantillas · Más control · Mejores resultados — Pack Plantillas Perú

Sheet Ingresos
A1: REGISTRO DE INGRESOS — MERCADO DE ABASTOS
A2: Registra cada venta o ingreso aquí; el Panel se actualiza solo
A4: Fecha | B4: Comprobante | C4: Cliente | D4: Detalle | E4: Cant. | F4: Precio Unit. | G4: Total | H4: Mes
A5: 46129 | B5: Boleta | C5: Maria Lopez S.A.C. | D5: Puesto de especias | E5: 6 | F5: 32.4 | G5: =E5*F5 | H5: Abr
A6: 46033 | B6: Boleta | C6: Mercado Central | D6: Puesto de frutas | E6: 1 | F6: 33.7 | G6: =E6*F6 | H6: Ene
A7: 46122 | B7: Boleta | C7: Inversiones Norte E.I.R.L. | D7: Puesto de frutas | E7: 5 | F7: 47.9 | G7: =E7*F7 | H7: Abr
A8: 46135 | B8: Factura | C8: Juan Pérez | D8: Puesto de carnes | E8: 6 | F8: 61 | G8: =E8*F8 | H8: Abr
A9: 46113 | B9: Factura | C9: Juan Pérez | D9: Puesto de abarrotes | E9: 8 | F9: 25.6 | G9: =E9*F9 | H9: Abr
A10: 46176 | B10: Factura | C10: Lucía Fernández | D10: Puesto de menestras | E10: 3 | F10: 12.8 | G10: =E10*F10 | H10: Jun
A11: 46224 | B11: Factura | C11: Juan Pérez | D11: Puesto de menestras | E11: 7 | F11: 60.4 | G11: =E11*F11 | H11: Jul
A12: 46115 | B12: Boleta | C12: Juan Pérez | D12: Puesto de especias | E12: 4 | F12: 36.3 | G12: =E12*F12 | H12: Abr
A13: 46229 | B13: Boleta | C13: Mercado Central | D13: Puesto de especias | E13: 6 | F13: 24.8 | G13: =E13*F13 | H13: Jul
A14: 46192 | B14: Factura | C14: Inversiones Norte E.I.R.L. | D14: Puesto de lácteos | E14: 1 | F14: 9.1 | G14: =E14*F14 | H14: Jun
A15: 46190 | B15: Factura | C15: Lucía Fernández | D15: Puesto de especias | E15: 3 | F15: 39.9 | G15: =E15*F15 | H15: Jun
A16: 46132 | B16: Factura | C16: Inversiones Norte E.I.R.L. | D16: Puesto de frutas | E16: 2 | F16: 45 | G16: =E16*F16 | H16: Abr
... A28: 46106 | B28: Factura | C28: Inversiones Norte E.I.R.L. | D28: Puesto de carnes | E28: 3 | F28: 40.8 | G28: =E28*F28 | H28: Mar
A30: 💡 Agrega más filas copiando el formato. La columna Total ya tiene la fórmula.
A32: Mercado de Abastos · Plantilla profesional Pack Perú

Sheet Gastos
A1: REGISTRO DE GASTOS — MERCADO DE ABASTOS
A2: Registra cada gasto con su categoría
A4: Fecha | B4: Comprobante | C4: Categoría | D4: Detalle | E4: Cant. | F4: Costo Unit. | G4: Total | H4: Mes
A5: 46096 | B5: Factura | C5: Alquiler | D5: Sueldo quincenal | E5: 1 | F5: 48.49 | G5: =E5*F5 | H5: Mar
A6: 46090 | B6: Factura | C6: Transporte | D6: Compra de insumos | E6: 1 | F6: 33.75 | G6: =E6*F6 | H6: Mar
A7: 46107 | B7: Factura | C7: Insumos | D7: Alquiler del local | E7: 1 | F7: 241.06 | G7: =E7*F7 | H7: Mar
A8: 46065 | B8: Factura | C8: Transporte | D8: Gasolina | E8: 1 | F8: 330.59 | G8: =E8*F8 | H8: Feb
A9: 46106 | B9: Factura | C9: Insumos | D9: Compra de insumos | E9: 1 | F9: 372.44 | G9: =E9*F9 | H9: Mar
A10: 46132 | B10: Factura | C10: Alquiler | D10: Alquiler del local | E10: 1 | F10: 161.12 | G10: =E10*F10 | H10: Abr
A11: 46072 | B11: Factura | C11: Transporte | D11: Sueldo quincenal | E11: 1 | F11: 117.28 | G11: =E11*F11 | H11: Feb
A12: 46064 | B12: Factura | C12: Marketing | D12: Compra de insumos | E12: 1 | F12: 212.25 | G12: =E12*F12 | H12: Feb
A13: 46126 | B13: Factura | C13: Personal | D13: Publicidad en Facebook | E13: 1 | F13: 313.9 | G13: =E13*F13 | H13: Abr
A14: 46139 | B14: Factura | C14: Personal | D14: Publicidad en Facebook | E14: 1 | F14: 177.65 | G14: =E14*F14 | H14: Abr
A15: 46077 | B15: Factura | C15: Servicios | D15: Compra de insumos | E15: 1 | F15: 50.31 | G15: =E15*F15 | H15: Feb
A16: 46115 | B16: Factura | C16: Alquiler | D16: Compra de insumos | E16: 1 | F16: 211.38 | G16: =E16*F16 | H16: Abr
... A24: 46181 | B24: Factura | C24: Insumos | D24: Recibo de luz | E24: 1 | F24: 48.57 | G24: =E24*F24 | H24: Jun
A32: Mercado de Abastos · Plantilla profesional Pack Perú
