Workbook

Sheet Resumen
A1: CONTROL DE VENTAS — CARPINTERÍA
A2: Resumen automático de tu actividad comercial
A4: VENTAS TOTALES | D4: N° DE VENTAS
A5: =SUM(Ventas!G5:G34) | D5: =COUNTA(Ventas!A5:A34)
A7: TICKET PROMEDIO | D7: UNIDADES VENDIDAS
A8: =IF(COUNTA(Ventas!A5:A34)=0,0,SUM(Ventas!G5:G34)/COUNTA(Ventas!A5:A34)) | D8: =SUM(Ventas!E5:E34)
A12: VENTAS POR MES | D12: TOP PRODUCTOS / SERVICIOS
A13: Mes | B13: Importe | C13: % del total | D13: Producto | E13: Unidades | F13: Importe
A14: Ene | B14: =SUMIF(Ventas!$H:$H,A14,Ventas!$G:$G) | C14: =IF(SUM(Ventas!$G$5:$G$34)=0,0,B14/SUM(Ventas!$G$5:$G$34)) | D14: Puerta de madera | E14: =SUMIF(Ventas!$D:$D,D14,Ventas!$E:$E) | F14: =SUMIF(Ventas!$D:$D,D14,Ventas!$G:$G)
A15: Feb | B15: =SUMIF(Ventas!$H:$H,A15,Ventas!$G:$G) | C15: =IF(SUM(Ventas!$G$5:$G$34)=0,0,B15/SUM(Ventas!$G$5:$G$34)) | D15: Clóset | E15: =SUMIF(Ventas!$D:$D,D15,Ventas!$E:$E) | F15: =SUMIF(Ventas!$D:$D,D15,Ventas!$G:$G)
A16: Mar | B16: =SUMIF(Ventas!$H:$H,A16,Ventas!$G:$G) | C16: =IF(SUM(Ventas!$G$5:$G$34)=0,0,B16/SUM(Ventas!$G$5:$G$34)) | D16: Mueble de cocina | E16: =SUMIF(Ventas!$D:$D,D16,Ventas!$E:$E) | F16: =SUMIF(Ventas!$D:$D,D16,Ventas!$G:$G)
A17: Abr | B17: =SUMIF(Ventas!$H:$H,A17,Ventas!$G:$G) | C17: =IF(SUM(Ventas!$G$5:$G$34)=0,0,B17/SUM(Ventas!$G$5:$G$34)) | D17: Escritorio | E17: =SUMIF(Ventas!$D:$D,D17,Ventas!$E:$E) | F17: =SUMIF(Ventas!$D:$D,D17,Ventas!$G:$G)
A18: May | B18: =SUMIF(Ventas!$H:$H,A18,Ventas!$G:$G) | C18: =IF(SUM(Ventas!$G$5:$G$34)=0,0,B18/SUM(Ventas!$G$5:$G$34)) | D18: Repisa | E18: =SUMIF(Ventas!$D:$D,D18,Ventas!$E:$E) | F18: =SUMIF(Ventas!$D:$D,D18,Ventas!$G:$G)
A19: Jun | B19: =SUMIF(Ventas!$H:$H,A19,Ventas!$G:$G) | C19: =IF(SUM(Ventas!$G$5:$G$34)=0,0,B19/SUM(Ventas!$G$5:$G$34)) | D19: Mueble de baño | E19: =SUMIF(Ventas!$D:$D,D19,Ventas!$E:$E) | F19: =SUMIF(Ventas!$D:$D,D19,Ventas!$G:$G)
A20: Jul | B20: =SUMIF(Ventas!$H:$H,A20,Ventas!$G:$G) | C20: =IF(SUM(Ventas!$G$5:$G$34)=0,0,B20/SUM(Ventas!$G$5:$G$34)) | D20: Vestidor | E20: =SUMIF(Ventas!$D:$D,D20,Ventas!$E:$E) | F20: =SUMIF(Ventas!$D:$D,D20,Ventas!$G:$G)
A21: Ago | B21: =SUMIF(Ventas!$H:$H,A21,Ventas!$G:$G) | C21: =IF(SUM(Ventas!$G$5:$G$34)=0,0,B21/SUM(Ventas!$G$5:$G$34)) | D21: Reparación de muebles | E21: =SUMIF(Ventas!$D:$D,D21,Ventas!$E:$E) | F21: =SUMIF(Ventas!$D:$D,D21,Ventas!$G:$G)
A22: Sep | B22: =SUMIF(Ventas!$H:$H,A22,Ventas!$G:$G) | C22: =IF(SUM(Ventas!$G$5:$G$34)=0,0,B22/SUM(Ventas!$G$5:$G$34))
A23: Oct | B23: =SUMIF(Ventas!$H:$H,A23,Ventas!$G:$G) | C23: =IF(SUM(Ventas!$G$5:$G$34)=0,0,B23/SUM(Ventas!$G$5:$G$34))
A24: Nov | B24: =SUMIF(Ventas!$H:$H,A24,Ventas!$G:$G) | C24: =IF(SUM(Ventas!$G$5:$G$34)=0,0,B24/SUM(Ventas!$G$5:$G$34))
A25: Dic | B25: =SUMIF(Ventas!$H:$H,A25,Ventas!$G:$G) | C25: =IF(SUM(Ventas!$G$5:$G$34)=0,0,B25/SUM(Ventas!$G$5:$G$34))
A33: Carpintería · Plantilla profesional Pack Perú

Sheet Ventas
A1: REGISTRO DE VENTAS — CARPINTERÍA
A2: Cada venta que registres alimenta el Resumen automáticamente
A4: Fecha | B4: Comprobante | C4: Cliente | D4: Producto/Servicio | E4: Cant. | F4: Precio Unit. | G4: Total | H4: Mes
A5: 46098 | B5: Boleta | C5: Inversiones Norte E.I.R.L. | D5: Escritorio | E5: 1 | F5: 47.2 | G5: =E5*F5 | H5: Mar
A6: 46155 | B6: Factura | C6: Lucía Fernández | D6: Puerta de madera | E6: 4 | F6: 43.4 | G6: =E6*F6 | H6: May
A7: 46153 | B7: Factura | C7: Roberto Castillo | D7: Puerta de madera | E7: 6 | F7: 56.8 | G7: =E7*F7 | H7: May
A8: 46057 | B8: Boleta | C8: Mercado Central | D8: Clóset | E8: 5 | F8: 35.7 | G8: =E8*F8 | H8: Feb
A9: 46129 | B9: Factura | C9: Comercial Andina | D9: Escritorio | E9: 1 | F9: 50.6 | G9: =E9*F9 | H9: Abr
A10: 46080 | B10: Factura | C10: Lucía Fernández | D10: Escritorio | E10: 3 | F10: 45.5 | G10: =E10*F10 | H10: Feb
A11: 46190 | B11: Boleta | C11: Juan Pérez | D11: Mueble de baño | E11: 5 | F11: 21.6 | G11: =E11*F11 | H11: Jun
A12: 46073 | B12: Boleta | C12: Distribuidora Sur | D12: Repisa | E12: 6 | F12: 11.2 | G12: =E12*F12 | H12: Feb
A13: 46215 | B13: Boleta | C13: Roberto Castillo | D13: Clóset | E13: 1 | F13: 52.9 | G13: =E13*F13 | H13: Jul
A14: 46158 | B14: Factura | C14: Comercial Andina | D14: Repisa | E14: 2 | F14: 54.3 | G14: =E14*F14 | H14: May
A15: 46224 | B15: Boleta | C15: Juan Pérez | D15: Repisa | E15: 2 | F15: 23.9 | G15: =E15*F15 | H15: Jul
A16: 46156 | B16: Factura | C16: Comercial Andina | D16: Mueble de baño | E16: 1 | F16: 36.4 | G16: =E16*F16 | H16: May
... A34: 46221 | B34: Boleta | C34: Roberto Castillo | D34: Mueble de cocina | E34: 3 | F34: 49.2 | G34: =E34*F34 | H34: Jul
