Workbook

Sheet Presupuesto
A1: PRESUPUESTO ANUAL 2026 — SERVICIOS ELÉCTRICOS
A2: Compara lo planificado contra lo ejecutado, mes por mes
A4: PRESUPUESTO VS EJECUTADO POR MES
A5: Mes | B5: Presupuestado | C5: Ejecutado | D5: Desviación S/ | E5: Desviación % | F5: Estado
A6: Ene | B6: 4601.68 | C6: 3553.15 | D6: =IF(C6="","",B6-C6) | E6: =IF(C6="","",D6/B6) | F6: =IF(C6="","Pendiente",IF(C6<=B6,"En meta","Excedido"))
A7: Feb | B7: 4497.58 | C7: 4926.66 | D7: =IF(C7="","",B7-C7) | E7: =IF(C7="","",D7/B7) | F7: =IF(C7="","Pendiente",IF(C7<=B7,"En meta","Excedido"))
A8: Mar | B8: 4755.39 | C8: 5127.96 | D8: =IF(C8="","",B8-C8) | E8: =IF(C8="","",D8/B8) | F8: =IF(C8="","Pendiente",IF(C8<=B8,"En meta","Excedido"))
A9: Abr | B9: 4760.24 | C9: 4960.34 | D9: =IF(C9="","",B9-C9) | E9: =IF(C9="","",D9/B9) | F9: =IF(C9="","Pendiente",IF(C9<=B9,"En meta","Excedido"))
A10: May | B10: 4793.46 | C10: 4374.65 | D10: =IF(C10="","",B10-C10) | E10: =IF(C10="","",D10/B10) | F10: =IF(C10="","Pendiente",IF(C10<=B10,"En meta","Excedido"))
A11: Jun | B11: 5094.47 | C11: 5522.04 | D11: =IF(C11="","",B11-C11) | E11: =IF(C11="","",D11/B11) | F11: =IF(C11="","Pendiente",IF(C11<=B11,"En meta","Excedido"))
A12: Jul | B12: 5017.72 | C12: 5907.43 | D12: =IF(C12="","",B12-C12) | E12: =IF(C12="","",D12/B12) | F12: =IF(C12="","Pendiente",IF(C12<=B12,"En meta","Excedido"))
A13: Ago | B13: 5128.61 | D13: =IF(C13="","",B13-C13) | E13: =IF(C13="","",D13/B13) | F13: =IF(C13="","Pendiente",IF(C13<=B13,"En meta","Excedido"))
A14: Sep | B14: 5159.35 | D14: =IF(C14="","",B14-C14) | E14: =IF(C14="","",D14/B14) | F14: =IF(C14="","Pendiente",IF(C14<=B14,"En meta","Excedido"))
A15: Oct | B15: 5110.42 | D15: =IF(C15="","",B15-C15) | E15: =IF(C15="","",D15/B15) | F15: =IF(C15="","Pendiente",IF(C15<=B15,"En meta","Excedido"))
A16: Nov | B16: 5142.73 | D16: =IF(C16="","",B16-C16) | E16: =IF(C16="","",D16/B16) | F16: =IF(C16="","Pendiente",IF(C16<=B16,"En meta","Excedido"))
A17: Dic | B17: 5274.06 | D17: =IF(C17="","",B17-C17) | E17: =IF(C17="","",D17/B17) | F17: =IF(C17="","Pendiente",IF(C17<=B17,"En meta","Excedido"))
A18: TOTAL AÑO | B18: =SUM(B6:B17) | C18: =SUM(C6:C17) | D18: =B18-C18 | E18: =D18/B18
A21: POR CATEGORÍA (se calcula desde la hoja Registro)
A22: Categoría | B22: Presupuesto Anual | C22: Ejecutado Acumulado | D22: Saldo | E22: Avance %
A23: Insumos | B23: 8715 | C23: =SUMIF(Registro!$B:$B,A23,Registro!$D:$D) | D23: =B23-C23 | E23: =IF(B23=0,0,C23/B23)
A24: Alquiler | B24: 4421 | C24: =SUMIF(Registro!$B:$B,A24,Registro!$D:$D) | D24: =B24-C24 | E24: =IF(B24=0,0,C24/B24)
A25: Servicios | B25: 4298 | C25: =SUMIF(Registro!$B:$B,A25,Registro!$D:$D) | D25: =B25-C25 | E25: =IF(B25=0,0,C25/B25)
A26: Personal | B26: 8606 | C26: =SUMIF(Registro!$B:$B,A26,Registro!$D:$D) | D26: =B26-C26 | E26: =IF(B26=0,0,C26/B26)
A27: Marketing | B27: 4402 | C27: =SUMIF(Registro!$B:$B,A27,Registro!$D:$D) | D27: =B27-C27 | E27: =IF(B27=0,0,C27/B27)
A28: Transporte | B28: 4252 | C28: =SUMIF(Registro!$B:$B,A28,Registro!$D:$D) | D28: =B28-C28 | E28: =IF(B28=0,0,C28/B28)
A30: 💡 Ajusta los montos presupuestados a la realidad de tu negocio.
A32: Servicios Eléctricos · Plantilla profesional Pack Perú

Sheet Registro
A1: REGISTRO DE EJECUCIÓN — SERVICIOS ELÉCTRICOS
A2: Registra cada gasto ejecutado con su categoría
A4: Fecha | B4: Categoría | C4: Concepto | D4: Monto
A5: 46205 | B5: Marketing | C5: Gasto operativo | D5: 144.07
A6: 46026 | B6: Personal | C6: Mantenimiento | D6: 653.8
A7: 46077 | B7: Alquiler | C7: Compra mensual | D7: 115.18
A8: 46085 | B8: Transporte | C8: Pago de servicios | D8: 755.28
A9: 46207 | B9: Alquiler | C9: Mantenimiento | D9: 217.2
A10: 46072 | B10: Personal | C10: Mantenimiento | D10: 146.47
A11: 46059 | B11: Insumos | C11: Compra mensual | D11: 410.46
A12: 46067 | B12: Alquiler | C12: Pago de servicios | D12: 172.93
A13: 46219 | B13: Servicios | C13: Gasto operativo | D13: 641.24
A14: 46038 | B14: Insumos | C14: Gasto operativo | D14: 442.18
A15: 46215 | B15: Servicios | C15: Mantenimiento | D15: 414.45
A16: 46058 | B16: Insumos | C16: Gasto operativo | D16: 191.79
... A26: 46218 | B26: Insumos | C26: Pago de servicios | D26: 602.02
